generator/Tgan.py
generator/__init__.py
generator/new_gan.py
models/__init__.py
models/optimizer.py
models/swint.py
models/movinet/__init__.py
models/movinet/config.py
models/movinet/models.py
models/vivit/__init__.py
models/vivit/module.py
models/vivit/vivit.py
optim/__init__.py
optim/approximate_gradients.py
train/__init__.py
train/train_blackbox.py
train/train_greybox.py
utils/__init__.py
utils/custom_loss.py
utils/dataloader.py
utils/videoTransforms.py
vidmodex-0.9a0.dist-info/METADATA
vidmodex-0.9a0.dist-info/WHEEL
vidmodex-0.9a0.dist-info/top_level.txt
vidmodex-0.9a0.dist-info/RECORD
