Metadata-Version: 2.1
Name: vidmodex
Version: 0.9a0
Summary: Code for Model Extration for Video Classification for Kinetics 400/600 trained model
Home-page: https://github.com/hex-plex/vidmodex
Author: Somnath Kumar
Author-email: hexplex0xff@gmail.com
License: UNKNOWN
Platform: UNKNOWN
